pynife/__init__.py
pynife/data.py
pynife/dataset_vault.py
pynife/embedding.py
pynife/losses.py
pynife/nife.py
pynife/utilities.py
pynife/version.py
pynife/cards/dataset_card.py
pynife/cards/model_card.md
pynife/cards/model_card.py
pynife/distillation/infer.py
pynife/distillation/utilities.py
pynife/initialization/__init__.py
pynife/initialization/model.py
pynife/tokenizer/count_vocabulary.py
pynife/tokenizer/datamodels.py
pynife/tokenizer/expand.py
pynife-0.1.0.dist-info/licenses/LICENSE
pynife-0.1.0.dist-info/METADATA
pynife-0.1.0.dist-info/WHEEL
pynife-0.1.0.dist-info/top_level.txt
pynife-0.1.0.dist-info/RECORD
