Metadata-Version: 2.4
Name: pynife
Version: 0.1.0
Summary: Nearly Inference Free embedding models in python
Requires-Python: >=3.10
License-File: LICENSE
Requires-Dist: transformers[torch]
Requires-Dist: sentence-transformers
Requires-Dist: numpy
Requires-Dist: datasets
Requires-Dist: skeletoken>=0.2.2
Requires-Dist: wandb
Requires-Dist: jinja2
Provides-Extra: dev
Requires-Dist: ipython; extra == "dev"
Requires-Dist: mypy; extra == "dev"
Requires-Dist: pre-commit; extra == "dev"
Requires-Dist: pytest; extra == "dev"
Requires-Dist: pytest-coverage; extra == "dev"
Requires-Dist: ruff; extra == "dev"
Dynamic: license-file
